<?xml version="1.0" encoding="UTF-8"?>
<!DOCTYPE service-builder PUBLIC "-//Liferay//DTD Service Builder 6.2.0//EN" "http://www.liferay.com/dtd/liferay-service-builder_6_2_0.dtd">
<service-builder package-path="com.rcs.service">
	<author>flor</author>
	<namespace>editor</namespace>
	<entity name="MessageSource" local-service="true" remote-service="false">

        <!-- PK fields -->
        
        <column name="key" type="String" primary="true" />        
        <column name="locale" type="String" primary="true" />                              
        
        
        <!-- Other fields -->
        		
        <column name="value" type="String" />                       
        <column name="bundle" type="String" />
        
		<!-- Order -->

		<order by="asc">
			<order-column name="key" />
		</order>
		
		<!-- Finder methods -->

		<finder name="Key" return-type="Collection">
			<finder-column name="key" />
		</finder>
		
		<finder name="Bundle" return-type="Collection">
			<finder-column name="bundle" />
		</finder>
		
		<finder name="KeyAndLocale" return-type="MessageSource">
			<finder-column name="key" />
			<finder-column name="locale" />			
		</finder>	
    </entity>    
</service-builder>
